<?xml version="1.0" encoding="UTF-8" ?>
<!-- Generated by Oracle SOA Modeler version 11.1.1.7.0 at [2/13/17 10:40 AM]. -->
<composite name="HavenAcedsIncomeInquiryService" revision="1.0"
           label="2017-02-13_10-40-04_857" mode="active" state="on"
           xmlns="http://xmlns.oracle.com/sca/1.0"
           xmlns:xs="http://www.w3.org/2001/XMLSchema"
           xmlns:wsp="http://schemas.xmlsoap.org/ws/2004/09/policy"
           xmlns:orawsp="http://schemas.oracle.com/ws/2006/01/policy"
           xmlns:ui="http://xmlns.oracle.com/soa/designer/">
  <import namespace="http://namespace.softwareag.com/entirex/xml/mapping"
          location="oramds:/apps/DCAS/ESB/ACEDS/wsdl/DHSDCASWebservices.wsdl"
          importType="wsdl"/>
  <import namespace="http://xmlns.oracle.com/pcbpel/adapter/jms/SOA_APP/HavenAcedsIncomeInquiryService/ConsumeRequest"
          location="ConsumeRequest.wsdl" importType="wsdl"/>
  <import namespace="http://xmlns.oracle.com/pcbpel/adapter/jms/SOA_APP/HavenAcedsIncomeInquiryService/PublishResponse"
          location="PublishResponse.wsdl" importType="wsdl"/>
  <import namespace="http://namespace.softwareag.com/entirex/xml/mapping"
          location="DHSDCASWebservicesWrapper.wsdl" importType="wsdl"/>
  <service name="ConsumeRequest" ui:wsdlLocation="ConsumeRequest.wsdl">
    <interface.wsdl interface="http://xmlns.oracle.com/pcbpel/adapter/jms/SOA_APP/HavenAcedsIncomeInquiryService/ConsumeRequest#wsdl.interface(Consume_Message_ptt)"/>
    <binding.jca config="ConsumeRequest_jms.jca"/>
  </service>
  <property name="productVersion" type="xs:string" many="false">11.1.1.7.0</property>
  <component name="ACEDSIncomeService" version="2.0">
    <implementation.bpel src="ACEDSIncomeService.bpel"/>
    <property name="bpel.config.transaction" type="xs:string" many="false">required</property>
    <property name="bpel.config.oneWayDeliveryPolicy" type="xs:string"
              many="false">sync</property>
  </component>
  <reference name="ACEDS_IncomeInquiry"
             ui:wsdlLocation="oramds:/apps/DCAS/ESB/ACEDS/wsdl/DHSDCASWebservices.wsdl">
    <interface.wsdl interface="http://namespace.softwareag.com/entirex/xml/mapping#wsdl.interface(EISBATCHPort)"/>
    <binding.ws port="http://namespace.softwareag.com/entirex/xml/mapping#wsdl.endpoint(DHSDCASWebservices/EISBATCHSOAP12Port)"
                location="oramds:/apps/DCAS/ESB/ACEDS/wsdl/DHSDCASWebservices.wsdl"
                soapVersion="1.2">
      <property name="endpointURI" type="xs:string" many="false">oramds:/apps/DCAS/ESB/ACEDS/wsdl/DHSDCASWebservices.wsdl</property>
      <property name="weblogic.wsee.wsat.transaction.flowOption"
                type="xs:string" many="false">WSDLDriven</property>
      <property name="oracle.webservices.httpReadTimeout" type="xs:integer"
                many="false" override="may">30000</property>
    </binding.ws>
  </reference>
  <reference name="PublishResponse" ui:wsdlLocation="PublishResponse.wsdl">
    <interface.wsdl interface="http://xmlns.oracle.com/pcbpel/adapter/jms/SOA_APP/HavenAcedsIncomeInquiryService/PublishResponse#wsdl.interface(Produce_Message_ptt)"/>
    <binding.jca config="PublishResponse_jms.jca"/>
  </reference>
  <wire>
    <source.uri>ConsumeRequest</source.uri>
    <target.uri>ACEDSIncomeService/ConsumeRequest</target.uri>
  </wire>
  <wire>
    <source.uri>ACEDSIncomeService/PublishResponse</source.uri>
    <target.uri>PublishResponse</target.uri>
  </wire>
  <wire>
    <source.uri>ACEDSIncomeService/ACEDS_IncomeInquiry</source.uri>
    <target.uri>ACEDS_IncomeInquiry</target.uri>
  </wire>
</composite>
