<?xml version='1.0' encoding='UTF-8'?>
<!--Generated by Oracle SOA Modeler version 11.1.1.7.8 at [12/18/17 9:02 AM].-->
<composite name="HavenFiveYearBarService" revision="1.0" label="2017-08-24_21-56-01_326" mode="active" state="on" xmlns="http://xmlns.oracle.com/sca/1.0" xmlns:xs="http://www.w3.org/2001/XMLSchema" xmlns:wsp="http://schemas.xmlsoap.org/ws/2004/09/policy" xmlns:orawsp="http://schemas.oracle.com/ws/2006/01/policy" xmlns:ui="http://xmlns.oracle.com/soa/designer/">
   <import namespace="http://xmlns.oracle.com/Haven/HavenFiveYearBarService/FiveYearBarService" location="FiveYearBarService.wsdl" importType="wsdl"/>
   <import namespace="http://xmlns.oracle.com/pcbpel/adapter/db/Haven/HavenFiveYearBarService/HavenFiveYearBarService" location="HavenFiveYearBarService.wsdl" importType="wsdl"/>
   <import namespace="http://xmlns.oracle.com/pcbpel/adapter/db/Haven/HavenCuramUserLookupCmpService/FiveYearBarService" location="FiveYearBarService.wsdl" importType="wsdl"/>
   <import namespace="http://xmlns.oracle.com/pcbpel/adapter/db/Haven/HavenCuramUserLookupCmpService/FiveYearBarService" location="FiveYearBarServiceWrapper.wsdl" importType="wsdl"/>
   <service name="fiveyearbarservice_client_ep" ui:wsdlLocation="FiveYearBarService.wsdl">
      <interface.wsdl interface="http://xmlns.oracle.com/pcbpel/adapter/db/Haven/HavenCuramUserLookupCmpService/FiveYearBarService#wsdl.interface(FiveYearBarService_ptt)"/>
      <binding.ws port="http://xmlns.oracle.com/pcbpel/adapter/db/Haven/HavenCuramUserLookupCmpService/FiveYearBarService#wsdl.endpoint(fiveyearbarservice_client_ep/FiveYearBarService_pt)">
         <property name="weblogic.wsee.wsat.transaction.flowOption" type="xs:string" many="false">NEVER</property>
      </binding.ws>
   </service>
   <property name="productVersion" type="xs:string" many="false">11.1.1.7.8</property>
   <component name="FiveYearBarService" version="2.0">
      <implementation.bpel src="FiveYearBarService.bpel"/>
      <property name="bpel.config.transaction" type="xs:string" many="false">required</property>
      <property name="bpel.config.oneWayDeliveryPolicy" type="xs:string" many="false">async.persist</property>
   </component>
   <reference name="HavenFiveYearBarService" ui:wsdlLocation="HavenFiveYearBarService.wsdl">
      <interface.wsdl interface="http://xmlns.oracle.com/pcbpel/adapter/db/Haven/HavenFiveYearBarService/HavenFiveYearBarService#wsdl.interface(HavenFiveYearBarService_ptt)"/>
      <binding.jca config="HavenFiveYearBarService_db.jca"/>
      <property name="jca.retry.count" type="xs:int" many="false" override="may">4</property>
      <property name="jca.retry.interval" type="xs:int" many="false" override="may">1</property>
      <property name="jca.retry.backoff" type="xs:int" many="false" override="may">2</property>
      <property name="jca.retry.maxInterval" type="xs:string" many="false" override="may">120</property>
   </reference>
   <wire>
      <source.uri>FiveYearBarService/HavenFiveYearBarService</source.uri>
      <target.uri>HavenFiveYearBarService</target.uri>
   </wire>
   <wire>
      <source.uri>fiveyearbarservice_client_ep</source.uri>
      <target.uri>FiveYearBarService/fiveyearbarservice_client_ep</target.uri>
   </wire>
</composite>
